[{
  "日期": "2018-9-3",
  "客户盈亏率": "0.858%",
  "客户盈亏/元": "8.58",
  "天天利盈亏额/元": "12.26"
},
  {
    "日期": "2018-9-4",
    "客户盈亏率": "1.678%",
    "客户盈亏/元": "8.20",
    "天天利盈亏额/元": "11.72"
  },
  {
    "日期": "2018-9-5",
    "客户盈亏率": "0.838%",
    "客户盈亏/元": "-8.40",
    "天天利盈亏额/元": "-8.40"
  },
  {
    "日期": "2018-9-6",
    "客户盈亏率": "1.238%",
    "客户盈亏/元": "4.00",
    "天天利盈亏额/元": "5.72"
  },
  {
    "日期": "2018-9-7",
    "客户盈亏率": "0.732%",
    "客户盈亏/元": "-5.06",
    "天天利盈亏额/元": "-5.06"
  },
  {
    "日期": "2018-9-10",
    "客户盈亏率": "1.366%",
    "客户盈亏/元": "6.34",
    "天天利盈亏额/元": "9.06"
  },
  {
    "日期": "2018-9-11",
    "客户盈亏率": "0.496%",
    "客户盈亏/元": "-8.70",
    "天天利盈亏额/元": "-8.70"
  },
  {
    "日期": "2018-9-12",
    "客户盈亏率": "-1.590%",
    "客户盈亏/元": "-20.86",
    "天天利盈亏额/元": "-20.86"
  },
  {
    "日期": "2018-9-13",
    "客户盈亏率": "-3.572%",
    "客户盈亏/元": "-19.82",
    "天天利盈亏额/元": "-19.82"
  },
  {
    "日期": "2018-9-14",
    "客户盈亏率": "-2.721%",
    "客户盈亏/元": "8.51",
    "天天利盈亏额/元": "12.16"
  },
  {
    "日期": "2018-9-17",
    "客户盈亏率": "-1.748%",
    "客户盈亏/元": "9.73",
    "天天利盈亏额/元": "13.90"
  },
  {
    "日期": "2018-9-18",
    "客户盈亏率": "-3.234%",
    "客户盈亏/元": "-14.86",
    "天天利盈亏额/元": "-14.86"
  },
  {
    "日期": "2018-9-19",
    "客户盈亏率": "-6.102%",
    "客户盈亏/元": "-28.68",
    "天天利盈亏额/元": "-28.68"
  },
  {
    "日期": "2018-9-20",
    "客户盈亏率": "-7.754%",
    "客户盈亏/元": "-16.52",
    "天天利盈亏额/元": "-16.52"
  },
  {
    "日期": "2018-9-21",
    "客户盈亏率": "-5.441%",
    "客户盈亏/元": "23.13",
    "天天利盈亏额/元": "33.04"
  },
  {
    "日期": "2018-9-25",
    "客户盈亏率": "-3.128%",
    "客户盈亏/元": "23.13",
    "天天利盈亏额/元": "33.04"
  },
  {
    "日期": "2018-9-26",
    "客户盈亏率": "-1.486%",
    "客户盈亏/元": "16.42",
    "天天利盈亏额/元": "23.46"
  },
  {
    "日期": "2018-9-27",
    "客户盈亏率": "-2.354%",
    "客户盈亏/元": "-8.68",
    "天天利盈亏额/元": "-8.68"
  },
  {
    "日期": "2018-9-28",
    "客户盈亏率": "-1.745%",
    "客户盈亏/元": "6.09",
    "天天利盈亏额/元": "8.70"
  }]